kobold3/__init__.py
kobold3/core.py
kobold3-0.0.2.dist-info/entry_points.txt
kobold3-0.0.2.dist-info/LICENSE
kobold3-0.0.2.dist-info/WHEEL
kobold3-0.0.2.dist-info/METADATA
kobold3-0.0.2.dist-info/RECORD
