Metadata-Version: 2.1
Name: kobold3
Version: 0.0.2
Summary: a bold key-value store for knowledge and config management
License: MIT
Author: rcox771
Author-email: russ771@gmail.com
Requires-Python: >=3.9,<4.0
Classifier: License :: OSI Approved :: MIT License
Classifier: Programming Language :: Python :: 3
Classifier: Programming Language :: Python :: 3.9
Requires-Dist: fire (>=0.4.0,<0.5.0)
Requires-Dist: rich (>=10.1.0,<11.0.0)
